the_zen_of/__init__.py
the_zen_of/_modidx.py
the_zen_of/cpp.py
the_zen_of/javascript.py
the_zen_of/python.py
the_zen_of/setup.py
the_zen_of-0.1.dist-info/LICENSE
the_zen_of-0.1.dist-info/METADATA
the_zen_of-0.1.dist-info/WHEEL
the_zen_of-0.1.dist-info/entry_points.txt
the_zen_of-0.1.dist-info/top_level.txt
the_zen_of-0.1.dist-info/RECORD
