Metadata-Version: 2.1
Name: the-zen-of
Version: 0.1
Summary: zens of various languages and applications
Home-page: https://github.com/sizhky/https://github.com/sizhky/the-zen-of/
Author: sizhky
Author-email: sizhky@gmail.com
License: Apache Software License 2.0
Keywords: zen,language,application,product,development,developer
Classifier: Development Status :: 3 - Alpha
Classifier: Intended Audience :: Developers
Classifier: Natural Language :: English
Classifier: Programming Language :: Python :: 3.7
Classifier: Programming Language :: Python :: 3.8
Classifier: Programming Language :: Python :: 3.9
Classifier: Programming Language :: Python :: 3.10
Classifier: License :: OSI Approved :: Apache Software License
Requires-Python: >=3.7
License-File: LICENSE
Requires-Dist: typer
Provides-Extra: dev
